drukarnia_api/__init__.py
drukarnia_api/network/__init__.py
drukarnia_api/network/connection.py
drukarnia_api/network/cookie.py
drukarnia_api/network/exceptions.py
drukarnia_api/network/headers.py
drukarnia_api/network/utils.py
drukarnia_api/objects/__init__.py
drukarnia_api/objects/article.py
drukarnia_api/objects/author.py
drukarnia_api/objects/base_object.py
drukarnia_api/objects/comment.py
drukarnia_api/objects/search.py
drukarnia_api/objects/tag.py
drukarnia_api/shortcuts/__init__.py
drukarnia_api/shortcuts/class_generator.py
drukarnia_api-1.1.2.dist-info/LICENSE
drukarnia_api-1.1.2.dist-info/METADATA
drukarnia_api-1.1.2.dist-info/WHEEL
drukarnia_api-1.1.2.dist-info/top_level.txt
drukarnia_api-1.1.2.dist-info/RECORD
