Metadata-Version: 2.1
Name: drukarnia-api
Version: 1.1.2
Summary: wrapper for the Drukarnia API
Home-page: https://github.com/androu-sys/drukarnia-api
Author: Andrii Herts
License: MIT
Classifier: Intended Audience :: Developers
Classifier: License :: OSI Approved :: MIT License
Classifier: Programming Language :: Python
Classifier: Programming Language :: Python :: 3
Classifier: Programming Language :: Python :: 3.6
Classifier: Programming Language :: Python :: 3.7
Classifier: Programming Language :: Python :: 3.8
Classifier: Programming Language :: Python :: 3.9
Classifier: Operating System :: OS Independent
License-File: LICENSE
Requires-Dist: aiohttp (==3.8.4)
Requires-Dist: attrdict (==2.0.1)
Requires-Dist: fake-useragent (==1.1.3)
